ipulse_shared_base_ftredge/__init__.py
ipulse_shared_base_ftredge/enums/__init__.py
ipulse_shared_base_ftredge/enums/enums_actions.py
ipulse_shared_base_ftredge/enums/enums_ai_core.py
ipulse_shared_base_ftredge/enums/enums_alerts.py
ipulse_shared_base_ftredge/enums/enums_analysts.py
ipulse_shared_base_ftredge/enums/enums_data.py
ipulse_shared_base_ftredge/enums/enums_data_eng.py
ipulse_shared_base_ftredge/enums/enums_iam.py
ipulse_shared_base_ftredge/enums/enums_logging.py
ipulse_shared_base_ftredge/enums/enums_organizations.py
ipulse_shared_base_ftredge/enums/enums_pulse.py
ipulse_shared_base_ftredge/enums/enums_resources.py
ipulse_shared_base_ftredge/enums/enums_sector_fincore.py
ipulse_shared_base_ftredge/enums/enums_status.py
ipulse_shared_base_ftredge/enums/enums_units.py
ipulse_shared_base_ftredge/enums/merge_all_script.py
ipulse_shared_base_ftredge/logging/__init__.py
ipulse_shared_base_ftredge/logging/logging_handlers_and_formatters.py
ipulse_shared_base_ftredge/logging/setup_logging.py
ipulse_shared_base_ftredge/logging/struct_log.py
ipulse_shared_base_ftredge/status/__init__.py
ipulse_shared_base_ftredge/status/status_counts.py
ipulse_shared_base_ftredge/status/status_helpers.py
ipulse_shared_base_ftredge/status/status_tracking_mixin.py
ipulse_shared_base_ftredge/utils/__init__.py
ipulse_shared_base_ftredge/utils/filter_sorting.py
ipulse_shared_base_ftredge/utils/formating_and_type_casting.py
ipulse_shared_base_ftredge/utils/time_utils.py
ipulse_shared_base_ftredge/utils/uuids_and_namespaces.py
ipulse_shared_base_ftredge/validators/__init__.py
ipulse_shared_base_ftredge/validators/cerberus_validators.py
ipulse_shared_base_ftredge/validators/schema_registry_item_validators.py
ipulse_shared_base_ftredge-12.12.0.dist-info/licenses/LICENCE
ipulse_shared_base_ftredge-12.12.0.dist-info/METADATA
ipulse_shared_base_ftredge-12.12.0.dist-info/WHEEL
ipulse_shared_base_ftredge-12.12.0.dist-info/top_level.txt
ipulse_shared_base_ftredge-12.12.0.dist-info/RECORD
