Metadata-Version: 2.4
Name: ipulse_shared_base_ftredge
Version: 12.12.0
Summary: Shared Enums, Logger and other Base Utils for  Pulse Platform . Using AI for Asset Management and Financial Advisory.
Home-page: https://github.com/TheFutureEdge/ipulse_shared_base
Author: Russlan Ramdowar
License-File: LICENCE
Requires-Dist: google-cloud-logging~=3.13.0
Requires-Dist: google-cloud-error-reporting~=1.14.0
Requires-Dist: Cerberus~=1.3.8
Dynamic: author
Dynamic: home-page
Dynamic: license-file
Dynamic: requires-dist
Dynamic: summary
